extras/__init__.py
extras/add.py
dartastlatools-0.0.5.dist-info/METADATA
dartastlatools-0.0.5.dist-info/WHEEL
dartastlatools-0.0.5.dist-info/top_level.txt
dartastlatools-0.0.5.dist-info/RECORD
